tempstore/__init__.py
tempstore/tempstore.py
tempstore-1.0.6.dist-info/DESCRIPTION.rst
tempstore-1.0.6.dist-info/METADATA
tempstore-1.0.6.dist-info/RECORD
tempstore-1.0.6.dist-info/WHEEL
tempstore-1.0.6.dist-info/metadata.json
tempstore-1.0.6.dist-info/top_level.txt
