Metadata-Version: 2.0
Name: tempstore
Version: 1.0.6
Summary: A simple container for handling multiple tempfiles
Home-page: https://github.com/ryanrichholt/tempstore
Author: Ryan Richholt
Author-email: UNKNOWN
License: UNKNOWN
Keywords: temp tempfile tempdir
Platform: UNKNOWN
Classifier: Development Status :: 3 - Alpha
Classifier: Topic :: Utilities
Requires-Python: >=3
